{
  "meta_vibe": "Playful",
  "source": "youtube",
  "total": 92,
  "note": "Deduplicated - ready for Ananki",
  "songs": [
    {
      "artist": "HRVY",
      "song": "Million Ways",
      "spotify_id": "3wuR0YSNdT9rgWfFi1lctv",
      "spotify_uri": "spotify:track:3wuR0YSNdT9rgWfFi1lctv",
      "source_url": "https://youtube.com/watch?v=00AhT7bSJX0",
      "source": "youtube",
      "post_title": "Best Happy and Upbeat Songs - YouTube Playlist 2025",
      "comment_text": "can we just appreciate how good loren played this role",
      "comment_score": 7868,
      "playlist_id": "PLgzTt0k8mXzF2fleyxQ17JxeccHFC8Gxp"
    },
    {
      "artist": "Noisestorm",
      "song": "Crab Rave",
      "spotify_id": "4qDHt2ClApBBzDAvhNGWFd",
      "spotify_uri": "spotify:track:4qDHt2ClApBBzDAvhNGWFd",
      "source_url": "https://youtube.com/watch?v=cE0wfjsybIQ",
      "source": "youtube",
      "post_title": "Silly songs",
      "comment_text": "This is how every crab will celebrate when humanity falls to extinction",
      "comment_score": 59531,
      "playlist_id": "PL4HawrIBNjTdmLzIpE5569J_eSobLjLnb"
    },
    {
      "artist": "g3ox_em",
      "song": "GigaChad Theme - Phonk House Version",
      "spotify_id": "7mLWNwcvwRdEviz6SfYp8A",
      "spotify_uri": "spotify:track:7mLWNwcvwRdEviz6SfYp8A",
      "source_url": "https://youtube.com/watch?v=OVh0bMNSFss",
      "source": "youtube",
      "post_title": "Silly songs",
      "comment_text": "this song slap so hard it makes me wanna drift a tank instead of a car",
      "comment_score": 72339,
      "playlist_id": "PL4HawrIBNjTdmLzIpE5569J_eSobLjLnb"
    },
    {
      "artist": "Millyz",
      "song": "Invisible",
      "spotify_id": "5fvLmflLgC5shV5DeujV5L",
      "spotify_uri": "spotify:track:5fvLmflLgC5shV5DeujV5L",
      "source_url": "https://youtube.com/watch?v=R_PmBkan4g4",
      "source": "youtube",
      "post_title": "Silly songs",
      "comment_text": "Subscribe and get asthma removed",
      "comment_score": 646,
      "playlist_id": "PL4HawrIBNjTdmLzIpE5569J_eSobLjLnb"
    },
    {
      "artist": "Cartoons",
      "song": "Witch Doctor",
      "spotify_id": "5YZuePCawcrg0DJrWovPu7",
      "spotify_uri": "spotify:track:5YZuePCawcrg0DJrWovPu7",
      "source_url": "https://youtube.com/watch?v=TYgOlqinH7A",
      "source": "youtube",
      "post_title": "Funny songs 😂",
      "comment_text": "If every single one of you had given me money I could be living it up right now",
      "comment_score": 59045,
      "playlist_id": "PLuwGoi1jk1pFZEcQFp8j0XB0DfVCyJtJ2"
    },
    {
      "artist": "Fridayy",
      "song": "Don't Give It Away (with Chris Brown)",
      "spotify_id": "08asI88SX61HTmODdARkIA",
      "spotify_uri": "spotify:track:08asI88SX61HTmODdARkIA",
      "source_url": "https://youtube.com/watch?v=1EI5ahb3HZE",
      "source": "youtube",
      "post_title": "Funny songs 😂",
      "comment_text": "",
      "comment_score": 0,
      "playlist_id": "PLuwGoi1jk1pFZEcQFp8j0XB0DfVCyJtJ2"
    },
    {
      "artist": "Parry Gripp",
      "song": "Tacocat",
      "spotify_id": "07HNhB2WOd1HNsbNvyoQpQ",
      "spotify_uri": "spotify:track:07HNhB2WOd1HNsbNvyoQpQ",
      "source_url": "https://youtube.com/watch?v=1pH5c1JkhLU",
      "source": "youtube",
      "post_title": "Funny songs 😂",
      "comment_text": "",
      "comment_score": 0,
      "playlist_id": "PLuwGoi1jk1pFZEcQFp8j0XB0DfVCyJtJ2"
    },
    {
      "artist": "The Key of Awesome",
      "song": "\"That's What I Like\" Parody of Bruno Mars' \"That's What I Like\"",
      "spotify_id": "4hO9Pmc7IGf1pUWRQYQCbI",
      "spotify_uri": "spotify:track:4hO9Pmc7IGf1pUWRQYQCbI",
      "source_url": "https://youtube.com/watch?v=xhl_rQDGzzo",
      "source": "youtube",
      "post_title": "Funny songs 😂",
      "comment_text": "This song's lyrics are so random",
      "comment_score": 5208,
      "playlist_id": "PLuwGoi1jk1pFZEcQFp8j0XB0DfVCyJtJ2"
    },
    {
      "artist": "The Kiboomers",
      "song": "Go Bananas!",
      "spotify_id": "5luoACytauKR29kpChTpTd",
      "spotify_uri": "spotify:track:5luoACytauKR29kpChTpTd",
      "source_url": "https://youtube.com/watch?v=MFmr_TZLpS0",
      "source": "youtube",
      "post_title": "Funny songs 😂",
      "comment_text": "",
      "comment_score": 0,
      "playlist_id": "PLuwGoi1jk1pFZEcQFp8j0XB0DfVCyJtJ2"
    },
    {
      "artist": "Baltazar Lora",
      "song": "Her Name Is Midnight",
      "spotify_id": "0wRHnCGKOJZicQskB6QBIT",
      "spotify_uri": "spotify:track:0wRHnCGKOJZicQskB6QBIT",
      "source_url": "https://youtube.com/watch?v=JNsKvZo6MDs",
      "source": "youtube",
      "post_title": "Funny songs 😂",
      "comment_text": "SUBSCRIBE TO WALLIBEAR!!\nhttps://www.youtube.com/c/Wallibear",
      "comment_score": 9612,
      "playlist_id": "PLuwGoi1jk1pFZEcQFp8j0XB0DfVCyJtJ2"
    },
    {
      "artist": "Cedarmont Kids",
      "song": "Dry Bones",
      "spotify_id": "7C89h6DnvEjddMKck2sLQi",
      "spotify_uri": "spotify:track:7C89h6DnvEjddMKck2sLQi",
      "source_url": "https://youtube.com/watch?v=-AhAdII3yAc",
      "source": "youtube",
      "post_title": "Silly Songs",
      "comment_text": "",
      "comment_score": 0,
      "playlist_id": "PL6IRXtEvbvxK4dIizkBfvuz6kL1qMPAsg"
    },
    {
      "artist": "Cedarmont Kids",
      "song": "John Jacob Jingleheimer Schmidt",
      "spotify_id": "3URCxHgNVq1bNlszFlid7h",
      "spotify_uri": "spotify:track:3URCxHgNVq1bNlszFlid7h",
      "source_url": "https://youtube.com/watch?v=CVZHk0nt5j4",
      "source": "youtube",
      "post_title": "Silly Songs",
      "comment_text": "",
      "comment_score": 0,
      "playlist_id": "PL6IRXtEvbvxK4dIizkBfvuz6kL1qMPAsg"
    },
    {
      "artist": "Cedarmont Kids",
      "song": "Wise Man And The Foolish Man",
      "spotify_id": "47uEpQYuXWzW3alLmtotjm",
      "spotify_uri": "spotify:track:47uEpQYuXWzW3alLmtotjm",
      "source_url": "https://youtube.com/watch?v=3HVdbULOVHA",
      "source": "youtube",
      "post_title": "Silly Songs",
      "comment_text": "",
      "comment_score": 0,
      "playlist_id": "PL6IRXtEvbvxK4dIizkBfvuz6kL1qMPAsg"
    },
    {
      "artist": "Cedarmont Kids",
      "song": "O Be Careful, Little Eyes",
      "spotify_id": "0kaLUEWQM45DwrlJOkhVfL",
      "spotify_uri": "spotify:track:0kaLUEWQM45DwrlJOkhVfL",
      "source_url": "https://youtube.com/watch?v=Tn2bDV30o60",
      "source": "youtube",
      "post_title": "Silly Songs",
      "comment_text": "",
      "comment_score": 0,
      "playlist_id": "PL6IRXtEvbvxK4dIizkBfvuz6kL1qMPAsg"
    },
    {
      "artist": "Cedarmont Kids",
      "song": "Do Your Ears Hang Low?",
      "spotify_id": "6ItU9g4hG7Ul7aXUMQDQRG",
      "spotify_uri": "spotify:track:6ItU9g4hG7Ul7aXUMQDQRG",
      "source_url": "https://youtube.com/watch?v=IEvPV1jq6Vc",
      "source": "youtube",
      "post_title": "Silly Songs",
      "comment_text": "",
      "comment_score": 0,
      "playlist_id": "PL6IRXtEvbvxK4dIizkBfvuz6kL1qMPAsg"
    },
    {
      "artist": "Cedarmont Kids",
      "song": "Rocka My Soul",
      "spotify_id": "1IsqoPsPInBnPvgC4KGeLx",
      "spotify_uri": "spotify:track:1IsqoPsPInBnPvgC4KGeLx",
      "source_url": "https://youtube.com/watch?v=u0fQZZkokIU",
      "source": "youtube",
      "post_title": "Silly Songs",
      "comment_text": "",
      "comment_score": 0,
      "playlist_id": "PL6IRXtEvbvxK4dIizkBfvuz6kL1qMPAsg"
    },
    {
      "artist": "Cedarmont Kids",
      "song": "Skinny Marinky Dinky Dink",
      "spotify_id": "0bHgI6i2tw9mrYQVTFnpuA",
      "spotify_uri": "spotify:track:0bHgI6i2tw9mrYQVTFnpuA",
      "source_url": "https://youtube.com/watch?v=wCR8KYmbWto",
      "source": "youtube",
      "post_title": "Silly Songs",
      "comment_text": "",
      "comment_score": 0,
      "playlist_id": "PL6IRXtEvbvxK4dIizkBfvuz6kL1qMPAsg"
    },
    {
      "artist": "Cedarmont Kids",
      "song": "Fingers, Nose And Toes",
      "spotify_id": "1MATLZE4s4XVHLc1g23COI",
      "spotify_uri": "spotify:track:1MATLZE4s4XVHLc1g23COI",
      "source_url": "https://youtube.com/watch?v=nVW1jEmtIdM",
      "source": "youtube",
      "post_title": "Silly Songs",
      "comment_text": "",
      "comment_score": 0,
      "playlist_id": "PL6IRXtEvbvxK4dIizkBfvuz6kL1qMPAsg"
    },
    {
      "artist": "Cedarmont Kids",
      "song": "The Bear Went Over The Mountain",
      "spotify_id": "4BH39OEPibM9IId4LqlUia",
      "spotify_uri": "spotify:track:4BH39OEPibM9IId4LqlUia",
      "source_url": "https://youtube.com/watch?v=cechGm0FOmQ",
      "source": "youtube",
      "post_title": "Silly Songs",
      "comment_text": "",
      "comment_score": 0,
      "playlist_id": "PL6IRXtEvbvxK4dIizkBfvuz6kL1qMPAsg"
    },
    {
      "artist": "Cedarmont Kids",
      "song": "Who Built The Ark?",
      "spotify_id": "3u8AKvYOkEiAkU6yAZ6kf2",
      "spotify_uri": "spotify:track:3u8AKvYOkEiAkU6yAZ6kf2",
      "source_url": "https://youtube.com/watch?v=nc6wrjcKdac",
      "source": "youtube",
      "post_title": "Silly Songs",
      "comment_text": "",
      "comment_score": 0,
      "playlist_id": "PL6IRXtEvbvxK4dIizkBfvuz6kL1qMPAsg"
    },
    {
      "artist": "Cedarmont Kids",
      "song": "Bingo",
      "spotify_id": "6fRTFtQtHkWBmxIl5FOrgU",
      "spotify_uri": "spotify:track:6fRTFtQtHkWBmxIl5FOrgU",
      "source_url": "https://youtube.com/watch?v=_KjE79kC4CQ",
      "source": "youtube",
      "post_title": "Silly Songs",
      "comment_text": "",
      "comment_score": 0,
      "playlist_id": "PL6IRXtEvbvxK4dIizkBfvuz6kL1qMPAsg"
    },
    {
      "artist": "Cedarmont Kids",
      "song": "I Got Shoes",
      "spotify_id": "0kRwBU46pEuBJlEeIxpDGO",
      "spotify_uri": "spotify:track:0kRwBU46pEuBJlEeIxpDGO",
      "source_url": "https://youtube.com/watch?v=lymDzFO5jag",
      "source": "youtube",
      "post_title": "Silly Songs",
      "comment_text": "",
      "comment_score": 0,
      "playlist_id": "PL6IRXtEvbvxK4dIizkBfvuz6kL1qMPAsg"
    },
    {
      "artist": "Cedarmont Kids",
      "song": "Looby Loo",
      "spotify_id": "3I9rujcOfOYByJ5Hx1KtKb",
      "spotify_uri": "spotify:track:3I9rujcOfOYByJ5Hx1KtKb",
      "source_url": "https://youtube.com/watch?v=63OaljEGQdM",
      "source": "youtube",
      "post_title": "Silly Songs",
      "comment_text": "",
      "comment_score": 0,
      "playlist_id": "PL6IRXtEvbvxK4dIizkBfvuz6kL1qMPAsg"
    },
    {
      "artist": "Cedarmont Kids",
      "song": "Polly-Wolly-Doodle",
      "spotify_id": "4eP4PNXPeJy2PcdWeCb1LK",
      "spotify_uri": "spotify:track:4eP4PNXPeJy2PcdWeCb1LK",
      "source_url": "https://youtube.com/watch?v=Uy9mwxVyOuw",
      "source": "youtube",
      "post_title": "Silly Songs",
      "comment_text": "",
      "comment_score": 0,
      "playlist_id": "PL6IRXtEvbvxK4dIizkBfvuz6kL1qMPAsg"
    },
    {
      "artist": "Cedarmont Kids",
      "song": "Who Did (Swallow Jonah)",
      "spotify_id": "3krpvDrknkigMKTfb46DcL",
      "spotify_uri": "spotify:track:3krpvDrknkigMKTfb46DcL",
      "source_url": "https://youtube.com/watch?v=UZ5UeNOXbOQ",
      "source": "youtube",
      "post_title": "Silly Songs",
      "comment_text": "",
      "comment_score": 0,
      "playlist_id": "PL6IRXtEvbvxK4dIizkBfvuz6kL1qMPAsg"
    },
    {
      "artist": "Cedarmont Kids",
      "song": "Michael Finnigan",
      "spotify_id": "6fJlBtd1jGG1l5ABLySELy",
      "spotify_uri": "spotify:track:6fJlBtd1jGG1l5ABLySELy",
      "source_url": "https://youtube.com/watch?v=v67TFhJHOJA",
      "source": "youtube",
      "post_title": "Silly Songs",
      "comment_text": "",
      "comment_score": 0,
      "playlist_id": "PL6IRXtEvbvxK4dIizkBfvuz6kL1qMPAsg"
    },
    {
      "artist": "Cedarmont Kids",
      "song": "Oh, You Can't Get To Heaven",
      "spotify_id": "1nl0M9DAoZmVef4PEagrZx",
      "spotify_uri": "spotify:track:1nl0M9DAoZmVef4PEagrZx",
      "source_url": "https://youtube.com/watch?v=i0xUse6mQLU",
      "source": "youtube",
      "post_title": "Silly Songs",
      "comment_text": "",
      "comment_score": 0,
      "playlist_id": "PL6IRXtEvbvxK4dIizkBfvuz6kL1qMPAsg"
    },
    {
      "artist": "Cedarmont Kids",
      "song": "There's A Hole In The Bucket",
      "spotify_id": "4EV43LBcPYoGH7bDQFoxVi",
      "spotify_uri": "spotify:track:4EV43LBcPYoGH7bDQFoxVi",
      "source_url": "https://youtube.com/watch?v=A20QQSZsv4E",
      "source": "youtube",
      "post_title": "Silly Songs",
      "comment_text": "",
      "comment_score": 0,
      "playlist_id": "PL6IRXtEvbvxK4dIizkBfvuz6kL1qMPAsg"
    },
    {
      "artist": "Royalty Free Music Background",
      "song": "Peaceful Beats",
      "spotify_id": "7gzubLvAFYDDzOnvbDfigp",
      "spotify_uri": "spotify:track:7gzubLvAFYDDzOnvbDfigp",
      "source_url": "https://youtube.com/watch?v=2HYeRA_FQcs",
      "source": "youtube",
      "post_title": "Slow Funny Music (Background Instrumentals)",
      "comment_text": "",
      "comment_score": 0,
      "playlist_id": "PLf7lYWKmi2gGOr5yckibc8qZTrN23wcuY"
    },
    {
      "artist": "Corey Cott",
      "song": "Gigi",
      "spotify_id": "0sGdOB6i8gaOGzWlMDCvVN",
      "spotify_uri": "spotify:track:0sGdOB6i8gaOGzWlMDCvVN",
      "source_url": "https://youtube.com/watch?v=6RS_4_H72tY",
      "source": "youtube",
      "post_title": "Slow Funny Music (Background Instrumentals)",
      "comment_text": "When you’ve been paired with your crush for an assignment...",
      "comment_score": 86,
      "playlist_id": "PLf7lYWKmi2gGOr5yckibc8qZTrN23wcuY"
    },
    {
      "artist": "DJ Screw",
      "song": "Freestyle",
      "spotify_id": "70GgfwhffVltqGiNxCwIjF",
      "spotify_uri": "spotify:track:70GgfwhffVltqGiNxCwIjF",
      "source_url": "https://youtube.com/watch?v=yCPEWkhBppk",
      "source": "youtube",
      "post_title": "Slow Funny Music (Background Instrumentals)",
      "comment_text": "What does it remind you of?",
      "comment_score": 2,
      "playlist_id": "PLf7lYWKmi2gGOr5yckibc8qZTrN23wcuY"
    },
    {
      "artist": "Bug Hunter",
      "song": "Slow Burn",
      "spotify_id": "7q1eAkQHQbKcnMJqeNCuq2",
      "spotify_uri": "spotify:track:7q1eAkQHQbKcnMJqeNCuq2",
      "source_url": "https://youtube.com/watch?v=jeivxr7xfKo",
      "source": "youtube",
      "post_title": "Slow Funny Music (Background Instrumentals)",
      "comment_text": "🤣🤣 i love this face hahaha nice ❤️❤️",
      "comment_score": 5,
      "playlist_id": "PLf7lYWKmi2gGOr5yckibc8qZTrN23wcuY"
    },
    {
      "artist": "cupcakKe",
      "song": "Cartoons",
      "spotify_id": "2hOMwCEcW4lM0Ghm7W2Rgf",
      "spotify_uri": "spotify:track:2hOMwCEcW4lM0Ghm7W2Rgf",
      "source_url": "https://youtube.com/watch?v=4XcMqRLz-jc",
      "source": "youtube",
      "post_title": "Mischievous music",
      "comment_text": "Hands down the best episodes are when it's just Spongebob Patrick and Squidward.",
      "comment_score": 5788,
      "playlist_id": "PLSb1gwOvkEJeurLfMJ_c1JyBch70oJIoQ"
    },
    {
      "artist": "James Blunt",
      "song": "I Can't Hear the Music",
      "spotify_id": "1D7IbAU7NSezaHChEDYRkF",
      "spotify_uri": "spotify:track:1D7IbAU7NSezaHChEDYRkF",
      "source_url": "https://youtube.com/watch?v=PdpCiumca_U",
      "source": "youtube",
      "post_title": "Mischievous music",
      "comment_text": "This song emphasizes the deterioration of sanity",
      "comment_score": 2080,
      "playlist_id": "PLSb1gwOvkEJeurLfMJ_c1JyBch70oJIoQ"
    },
    {
      "artist": "Esham",
      "song": "Turbulence",
      "spotify_id": "7a2z2fq6Blw12Q5XJY9Bq1",
      "spotify_uri": "spotify:track:7a2z2fq6Blw12Q5XJY9Bq1",
      "source_url": "https://youtube.com/watch?v=j29HiooOlpU",
      "source": "youtube",
      "post_title": "Mischievous music",
      "comment_text": "At Least I'm Safe Inside My Mind",
      "comment_score": 789,
      "playlist_id": "PLSb1gwOvkEJeurLfMJ_c1JyBch70oJIoQ"
    },
    {
      "artist": "Blaqbonez",
      "song": "Prayers Up (feat. KindlyNxsh, Brotherkupa & Wave$tar)",
      "spotify_id": "6b4R6A3YFCjvkK6oPLOHwN",
      "spotify_uri": "spotify:track:6b4R6A3YFCjvkK6oPLOHwN",
      "source_url": "https://youtube.com/watch?v=he3HFcys9qk",
      "source": "youtube",
      "post_title": "Mischievous music",
      "comment_text": "10-ton hammer, strongest attack in all of One Piece!",
      "comment_score": 101,
      "playlist_id": "PLSb1gwOvkEJeurLfMJ_c1JyBch70oJIoQ"
    },
    {
      "artist": "MHRAP",
      "song": "VIBE ASUMA (Animes)",
      "spotify_id": "4OBnqHuUMS7RPQJ3w76ZWr",
      "spotify_uri": "spotify:track:4OBnqHuUMS7RPQJ3w76ZWr",
      "source_url": "https://youtube.com/watch?v=pR6_xQ08nM0",
      "source": "youtube",
      "post_title": "Mischievous music",
      "comment_text": "Sounds like a Mario Kart Theme.",
      "comment_score": 181,
      "playlist_id": "PLSb1gwOvkEJeurLfMJ_c1JyBch70oJIoQ"
    },
    {
      "artist": "Yugo Kanno",
      "song": "Stardust Crusaders",
      "spotify_id": "1xsExFad0m5ikHaejXZrcA",
      "spotify_uri": "spotify:track:1xsExFad0m5ikHaejXZrcA",
      "source_url": "https://youtube.com/watch?v=D5O_W8yDig4",
      "source": "youtube",
      "post_title": "Mischievous music",
      "comment_text": "\"AVDOL ! HURRY UP ! I'M CRYING !\nHELP ME ! OOH MY GOD !\"",
      "comment_score": 7127,
      "playlist_id": "PLSb1gwOvkEJeurLfMJ_c1JyBch70oJIoQ"
    },
    {
      "artist": "Yugo Kanno",
      "song": "Killer",
      "spotify_id": "21YiaS85ngOoYT773cMFlW",
      "spotify_uri": "spotify:track:21YiaS85ngOoYT773cMFlW",
      "source_url": "https://youtube.com/watch?v=8QPEVQp1MZw",
      "source": "youtube",
      "post_title": "Mischievous music",
      "comment_text": "The perfect ost to go on a date with your girlfriend",
      "comment_score": 18660,
      "playlist_id": "PLSb1gwOvkEJeurLfMJ_c1JyBch70oJIoQ"
    },
    {
      "artist": "Wolfgang Amadeus Mozart",
      "song": "Requiem, K. 626: Lacrimosa",
      "spotify_id": "3oHSL6pt9LpNrQZuQGu9wL",
      "spotify_uri": "spotify:track:3oHSL6pt9LpNrQZuQGu9wL",
      "source_url": "https://youtube.com/watch?v=k1-TrAvp_xs",
      "source": "youtube",
      "post_title": "Mischievous music",
      "comment_text": "*couldn't finish it but here you go*",
      "comment_score": 86399,
      "playlist_id": "PLSb1gwOvkEJeurLfMJ_c1JyBch70oJIoQ"
    },
    {
      "artist": "Tp & Esco",
      "song": "Mr. Fast 2witch",
      "spotify_id": "1m7ah4nKsKTwUtd9rqOjeo",
      "spotify_uri": "spotify:track:1m7ah4nKsKTwUtd9rqOjeo",
      "source_url": "https://youtube.com/watch?v=uXb4yhfByUQ",
      "source": "youtube",
      "post_title": "Mischievous music",
      "comment_text": "The Sniper as Rewritten by people who main the class\n\nSnipin's a bad job, mate.\nIt's difficult work, outta doors. I guarantee you will get backstabbed.\nAt the end of the day, long as there are three Snipers on the map, someone is gonna want some Sniper votekicked.\nI- ye- I'm not switching to be Medic, man.\nI'm a- Ye- Not a \"camper\", I'm an assassin! ...Well, the difference being one's a playstyle and the other's a 12-year-old playin' Call of Duty!\nI'll be honest with ya: my teammates do not care for it.\nI think this mate is a bot. (Instakills on killfeed) Yes, he is.\nFeelins'? Look mate, you know who has a lot of feelings? Blokes that run screaming into the front lines with a flamethrower. \nTryhards have no standards.\nBe annoying. Be repetitive.\nHave a plan to taunt everyone you bodyshot.",
      "comment_score": 10518,
      "playlist_id": "PLSb1gwOvkEJeurLfMJ_c1JyBch70oJIoQ"
    },
    {
      "artist": "Omori",
      "song": "Duet",
      "spotify_id": "5RzB3KcfvZgvsWcsETVsqG",
      "spotify_uri": "spotify:track:5RzB3KcfvZgvsWcsETVsqG",
      "source_url": "https://youtube.com/watch?v=1jQWgrgDlC4",
      "source": "youtube",
      "post_title": "Mischievous music",
      "comment_text": "\"This dungeon requires puzzle skills and patience to get out of-\"\n\nMARI: *pushes button* You're free!",
      "comment_score": 1380,
      "playlist_id": "PLSb1gwOvkEJeurLfMJ_c1JyBch70oJIoQ"
    },
    {
      "artist": "The Paper Chase",
      "song": "we have ways to make you talk (the human condition)",
      "spotify_id": "2wAbeugROspCNxMfWn1wou",
      "spotify_uri": "spotify:track:2wAbeugROspCNxMfWn1wou",
      "source_url": "https://youtube.com/watch?v=6MBFHl_E3AU",
      "source": "youtube",
      "post_title": "Mischievous music",
      "comment_text": "When you think about it, this entire zone is based off of a shitty Blackjack game Sunny has on his computer.",
      "comment_score": 2912,
      "playlist_id": "PLSb1gwOvkEJeurLfMJ_c1JyBch70oJIoQ"
    },
    {
      "artist": "Justine Skye",
      "song": "Collide (feat. Tyga)",
      "spotify_id": "5kY2DRIom6dcVZbQb1SAX8",
      "spotify_uri": "spotify:track:5kY2DRIom6dcVZbQb1SAX8",
      "source_url": "https://youtube.com/watch?v=NIaNB22YGPA",
      "source": "youtube",
      "post_title": "Mischievous playlist",
      "comment_text": "Such majestic,elegant,divine, ethereal Looking man✨... Its a shame he doesnt exist....But nevertheless,madly in love with this man so bad despite all anyway...😂 My glorious blue eyed king~💙",
      "comment_score": 16,
      "playlist_id": "PLCKpuI9Xni_DkT6dPEAw-MN7bOTIB_Gh9"
    },
    {
      "artist": "Connie Francis",
      "song": "Pretty Little Baby",
      "spotify_id": "5GQPBzoRBDxcAjwSSluQXD",
      "spotify_uri": "spotify:track:5GQPBzoRBDxcAjwSSluQXD",
      "source_url": "https://youtube.com/watch?v=LTsR3LfhdxI",
      "source": "youtube",
      "post_title": "Mischievous playlist",
      "comment_text": "I feel like she's smiling while singing",
      "comment_score": 7863,
      "playlist_id": "PLCKpuI9Xni_DkT6dPEAw-MN7bOTIB_Gh9"
    },
    {
      "artist": "Fujii Kaze",
      "song": "Shinunoga E-Wa",
      "spotify_id": "0o9zmvc5f3EFApU52PPIyW",
      "spotify_uri": "spotify:track:0o9zmvc5f3EFApU52PPIyW",
      "source_url": "https://youtube.com/watch?v=SobCVRdEiI0",
      "source": "youtube",
      "post_title": "Mischievous playlist",
      "comment_text": "3:01 The best part for playing a violin ✨",
      "comment_score": 1296,
      "playlist_id": "PLCKpuI9Xni_DkT6dPEAw-MN7bOTIB_Gh9"
    },
    {
      "artist": "FateD",
      "song": "Oh My Little Baby Boy",
      "spotify_id": "1Y7wTFIglJCYaB2uQH3zdS",
      "spotify_uri": "spotify:track:1Y7wTFIglJCYaB2uQH3zdS",
      "source_url": "https://youtube.com/watch?v=DDOLJayy9Cs",
      "source": "youtube",
      "post_title": "Mischievous playlist",
      "comment_text": "I love discovering this kind of old music. Makes the driving experience better",
      "comment_score": 2179,
      "playlist_id": "PLCKpuI9Xni_DkT6dPEAw-MN7bOTIB_Gh9"
    },
    {
      "artist": "The Palmer Squares",
      "song": "Bring the Bacon",
      "spotify_id": "2BjRTKFOXGznAhwJOZtMdr",
      "spotify_uri": "spotify:track:2BjRTKFOXGznAhwJOZtMdr",
      "source_url": "https://youtube.com/watch?v=QNYT9wVwQ8A",
      "source": "youtube",
      "post_title": "Mischievous playlist",
      "comment_text": "0% drugs \n0% alcohol \n0% sex\n100% STAY WITH MEEEEEE",
      "comment_score": 114761,
      "playlist_id": "PLCKpuI9Xni_DkT6dPEAw-MN7bOTIB_Gh9"
    },
    {
      "artist": "Andriel",
      "song": "Afrodite (album Version)",
      "spotify_id": "1xqa1mUMuYpbZRP9VukQP6",
      "spotify_uri": "spotify:track:1xqa1mUMuYpbZRP9VukQP6",
      "source_url": "https://youtube.com/watch?v=6zawxDsTkUI",
      "source": "youtube",
      "post_title": "Mischievous playlist",
      "comment_text": "POV: you’re trying to sleep but there’s a party going on in the apartment below you",
      "comment_score": 17430,
      "playlist_id": "PLCKpuI9Xni_DkT6dPEAw-MN7bOTIB_Gh9"
    },
    {
      "artist": "фрози",
      "song": "bounce (i just wanna dance)",
      "spotify_id": "7zirrBlMqY5UD6DIQa0Lut",
      "spotify_uri": "spotify:track:7zirrBlMqY5UD6DIQa0Lut",
      "source_url": "https://youtube.com/watch?v=UyLdI59lwyE",
      "source": "youtube",
      "post_title": "Mischievous playlist",
      "comment_text": "I've been looking for this song for 1 hour, and the happiness in my face I can't contain.",
      "comment_score": 5063,
      "playlist_id": "PLCKpuI9Xni_DkT6dPEAw-MN7bOTIB_Gh9"
    },
    {
      "artist": "KingST",
      "song": "Scarecrow",
      "spotify_id": "7a7f0P7FFn5S0t9GkjwbH2",
      "spotify_uri": "spotify:track:7a7f0P7FFn5S0t9GkjwbH2",
      "source_url": "https://youtube.com/watch?v=9JSNBnSIXQs",
      "source": "youtube",
      "post_title": "Mischievous playlist",
      "comment_text": "Lyrics:\n\nEyes don't lie\nEyes don't lie\nSay you're mine\nEyes don't lie\nCan't lie to you, baby\nWanna feel your body close\nYou say that you hate me\nThen tell me shit nobody knows\nYeah, you're beautiful, don't have to try\nDarling, you look divine\nEyes don't lie\nEyes don't lie\nSay you're mine\nEyes don't lie\nYou tell me your secrets\nYou keep your life between your lips\nYou know you're my weakness\nTell stories with your fingertips\nYeah, you're beautiful, don't have to try\nDarling, you look divine\nEyes don't lie\nEyes don't lie\nSay you're mine\nEyes don't lie\nI swear friends don't get this close\nPull you in, exchanging souls\nTrace my skin, losing control\nEyes don't lie\nEyes don't lie\nSay you're mine\nEyes don't lie",
      "comment_score": 154,
      "playlist_id": "PLCKpuI9Xni_DkT6dPEAw-MN7bOTIB_Gh9"
    },
    {
      "artist": "Isabel LaRosa",
      "song": "i'm yours",
      "spotify_id": "37vVp2sWHuuIBOSl1NswP6",
      "spotify_uri": "spotify:track:37vVp2sWHuuIBOSl1NswP6",
      "source_url": "https://youtube.com/watch?v=-gp2eNf_pMc",
      "source": "youtube",
      "post_title": "Mischievous playlist",
      "comment_text": "I have been counting down the days for this masterpiece to be released",
      "comment_score": 7875,
      "playlist_id": "PLCKpuI9Xni_DkT6dPEAw-MN7bOTIB_Gh9"
    },
    {
      "artist": "Isabel LaRosa",
      "song": "older",
      "spotify_id": "75c2zaSdDBSX0A8Jyvm4fO",
      "spotify_uri": "spotify:track:75c2zaSdDBSX0A8Jyvm4fO",
      "source_url": "https://youtube.com/watch?v=7MVaVDAi5A8",
      "source": "youtube",
      "post_title": "Mischievous playlist",
      "comment_text": "This hits different when you're actually in love with someone who's older than you.",
      "comment_score": 4689,
      "playlist_id": "PLCKpuI9Xni_DkT6dPEAw-MN7bOTIB_Gh9"
    },
    {
      "artist": "Eminem",
      "song": "Not Alike (feat. Royce Da 5'9)",
      "spotify_id": "28FGV3ORH14MYORd7s5dlU",
      "spotify_uri": "spotify:track:28FGV3ORH14MYORd7s5dlU",
      "source_url": "https://youtube.com/watch?v=WHAvoTZ1KpE",
      "source": "youtube",
      "post_title": "Mischievous playlist",
      "comment_text": "me when im around my crush and other ppl: Feels like in a hot edit :')",
      "comment_score": 63,
      "playlist_id": "PLCKpuI9Xni_DkT6dPEAw-MN7bOTIB_Gh9"
    },
    {
      "artist": "Artemas",
      "song": "i like the way you kiss me",
      "spotify_id": "2GxrNKugF82CnoRFbQfzPf",
      "spotify_uri": "spotify:track:2GxrNKugF82CnoRFbQfzPf",
      "source_url": "https://youtube.com/watch?v=bUU4eDJAs-Q",
      "source": "youtube",
      "post_title": "Mischievous playlist",
      "comment_text": "The beat is fire!! The lyrics aren't much, but they're addictive",
      "comment_score": 96,
      "playlist_id": "PLCKpuI9Xni_DkT6dPEAw-MN7bOTIB_Gh9"
    },
    {
      "artist": "J Hus",
      "song": "Daily Duppy (feat. GRM Daily)",
      "spotify_id": "1CBWQi8t0QqdEEXlXPuS6A",
      "spotify_uri": "spotify:track:1CBWQi8t0QqdEEXlXPuS6A",
      "source_url": "https://youtube.com/watch?v=Cjp6RVrOOW0",
      "source": "youtube",
      "post_title": "Mischievous playlist",
      "comment_text": "This is one of those songs that you hear for one second, then sigh, because you know you have to actually go and listen to it before being able to sleep",
      "comment_score": 35895,
      "playlist_id": "PLCKpuI9Xni_DkT6dPEAw-MN7bOTIB_Gh9"
    },
    {
      "artist": "Parallel Park",
      "song": "Watch Me Fall Apart",
      "spotify_id": "55CKmVv7EHCQ7hYZZwcddc",
      "spotify_uri": "spotify:track:55CKmVv7EHCQ7hYZZwcddc",
      "source_url": "https://youtube.com/watch?v=RUcZgZvATlU",
      "source": "youtube",
      "post_title": "Mischievous playlist",
      "comment_text": "This makes me feel at peace. Something hits different with this one.",
      "comment_score": 433,
      "playlist_id": "PLCKpuI9Xni_DkT6dPEAw-MN7bOTIB_Gh9"
    },
    {
      "artist": "SUICIDAL-IDOL",
      "song": "ecstacy (slowed)",
      "spotify_id": "1JgknGBbrfmEHeOZH051SS",
      "spotify_uri": "spotify:track:1JgknGBbrfmEHeOZH051SS",
      "source_url": "https://youtube.com/watch?v=lLxAbevUyIQ",
      "source": "youtube",
      "post_title": "Mischievous playlist",
      "comment_text": "WE MAKING IT OUT OF THE MENTAL HOSPITAL WITH THIS ONE 🔥🔥🔥",
      "comment_score": 20434,
      "playlist_id": "PLCKpuI9Xni_DkT6dPEAw-MN7bOTIB_Gh9"
    },
    {
      "artist": "MEG MYERS",
      "song": "Desire - Hucci Remix",
      "spotify_id": "27TNnB8XFuQN4ZmrcSKcR8",
      "spotify_uri": "spotify:track:27TNnB8XFuQN4ZmrcSKcR8",
      "source_url": "https://youtube.com/watch?v=E0hGQ4tEJhI",
      "source": "youtube",
      "post_title": "Mischievous playlist",
      "comment_text": "I mean, he's crazy, he's not okay, but he's too hot.",
      "comment_score": 12664,
      "playlist_id": "PLCKpuI9Xni_DkT6dPEAw-MN7bOTIB_Gh9"
    },
    {
      "artist": "slowbro",
      "song": "Starboy - slowed + reverb",
      "spotify_id": "6UMPhJBci5W7dGbGdIOn20",
      "spotify_uri": "spotify:track:6UMPhJBci5W7dGbGdIOn20",
      "source_url": "https://youtube.com/watch?v=NrSgWKx5l8w",
      "source": "youtube",
      "post_title": "Mischievous playlist",
      "comment_text": "1:08\nWhen you tell siri a joke",
      "comment_score": 19657,
      "playlist_id": "PLCKpuI9Xni_DkT6dPEAw-MN7bOTIB_Gh9"
    },
    {
      "artist": "Doonie",
      "song": "Triple 7 Aftalock - Remix",
      "spotify_id": "2yTCjK9I8n9xBMorL9rPa6",
      "spotify_uri": "spotify:track:2yTCjK9I8n9xBMorL9rPa6",
      "source_url": "https://youtube.com/watch?v=lRVJuPI5IXI",
      "source": "youtube",
      "post_title": "Mischievous playlist",
      "comment_text": "Why is no one talking about his INCREDIBLE piano skills??? That beginning part was just amazing!!",
      "comment_score": 96819,
      "playlist_id": "PLCKpuI9Xni_DkT6dPEAw-MN7bOTIB_Gh9"
    },
    {
      "artist": "3R2",
      "song": "Mischievous Princess",
      "spotify_id": "0c8af1u02UuaLcn9aamrDd",
      "spotify_uri": "spotify:track:0c8af1u02UuaLcn9aamrDd",
      "source_url": "https://youtube.com/watch?v=HhircuOpJoM",
      "source": "youtube",
      "post_title": "Mischievous Kiss: Love In Tokyo OST",
      "comment_text": "This song makes me want to go outside and run around the city in a pink dress....Huh, weird.",
      "comment_score": 2692,
      "playlist_id": "PLT3tJ_gu7fEICcW9mP8EOOV_XyYlVIEwq"
    },
    {
      "artist": "MAN V",
      "song": "U & ME",
      "spotify_id": "34gQUEcBQ7NpNsXqOU2Ekw",
      "spotify_uri": "spotify:track:34gQUEcBQ7NpNsXqOU2Ekw",
      "source_url": "https://youtube.com/watch?v=-GDtpQoqsDw",
      "source": "youtube",
      "post_title": "Mischievous Kiss: Love In Tokyo OST",
      "comment_text": "Hi! I really like this piece. Would you happen to have to have the sheet music for this?",
      "comment_score": 4,
      "playlist_id": "PLT3tJ_gu7fEICcW9mP8EOOV_XyYlVIEwq"
    },
    {
      "artist": "Drake",
      "song": "Push Ups",
      "spotify_id": "3eh51r6rFWAlGQRlHx9QnQ",
      "spotify_uri": "spotify:track:3eh51r6rFWAlGQRlHx9QnQ",
      "source_url": "https://youtube.com/watch?v=yVyh8myPtk4",
      "source": "youtube",
      "post_title": "Mischievous Kiss: Love In Tokyo OST",
      "comment_text": "Please share me this music sheet. ",
      "comment_score": 1,
      "playlist_id": "PLT3tJ_gu7fEICcW9mP8EOOV_XyYlVIEwq"
    },
    {
      "artist": "Jedi Mind Tricks",
      "song": "I Against I",
      "spotify_id": "0qw4HLV9qhjtImWR7oxZAO",
      "spotify_uri": "spotify:track:0qw4HLV9qhjtImWR7oxZAO",
      "source_url": "https://youtube.com/watch?v=QvazZScuexs",
      "source": "youtube",
      "post_title": "90s Whimsigothic 🌜🌞",
      "comment_text": "Came here because of lain, staying here for Boa",
      "comment_score": 668,
      "playlist_id": "PLER-zBw-Up-Ps5jKR4FEw5u7HLmve6hXf"
    },
    {
      "artist": "Steve Lawrence",
      "song": "My Claire De Lune",
      "spotify_id": "2zxcK81j4xPntEvBImvhKz",
      "spotify_uri": "spotify:track:2zxcK81j4xPntEvBImvhKz",
      "source_url": "https://youtube.com/watch?v=_j2b1jpNraE",
      "source": "youtube",
      "post_title": "Whimsical Music Playlist",
      "comment_text": "Claire de lune is one of those pieces that makes you nostalgic.  Like, you’ve heard it before, somewhere, in a memory from another life.",
      "comment_score": 8085,
      "playlist_id": "PLfr_88dG22s3J90Dm_bZkjC8D3kE-x_ta"
    },
    {
      "artist": "J-Live",
      "song": "Them That's Not",
      "spotify_id": "0bY6SdYZcid3fzp7im837v",
      "spotify_uri": "spotify:track:0bY6SdYZcid3fzp7im837v",
      "source_url": "https://youtube.com/watch?v=oj6PpKd7nVI",
      "source": "youtube",
      "post_title": "Whimsical Music Playlist",
      "comment_text": "Yo this is some magical cotton candy",
      "comment_score": 12941,
      "playlist_id": "PLfr_88dG22s3J90Dm_bZkjC8D3kE-x_ta"
    },
    {
      "artist": "Christy Altomare",
      "song": "Once Upon a December",
      "spotify_id": "4W37fDymJzsqaarlKKEvcM",
      "spotify_uri": "spotify:track:4W37fDymJzsqaarlKKEvcM",
      "source_url": "https://youtube.com/watch?v=JZ6buLNIgs8",
      "source": "youtube",
      "post_title": "Whimsical Music Playlist",
      "comment_text": "This sounds like the more realistic and sad story of Anastasia where, she actually you know, died with her family.... and she's a ghost just dancing to the music..",
      "comment_score": 23217,
      "playlist_id": "PLfr_88dG22s3J90Dm_bZkjC8D3kE-x_ta"
    },
    {
      "artist": "Epik High",
      "song": "우산 (feat. 윤하)",
      "spotify_id": "1VnjByC7TUx5A73A4qtgoo",
      "spotify_uri": "spotify:track:1VnjByC7TUx5A73A4qtgoo",
      "source_url": "https://youtube.com/watch?v=pi7rX5G7x48",
      "source": "youtube",
      "post_title": "Whimsical Music Playlist",
      "comment_text": "It's so crazy to think that over 7 billion people on this earth look at the same moon and sun, and that while one person is getting ready for work or school, another person is finishing up for the day getting ready to go home and enjoy their afternoon whether it be with family, friends or even alone. Where I'm at it's 3am rn and just reading all these comments it's crazy to think that 30 years ago this kind of thing wasn't even possible. I hope that whoever reads this comment has a great day/night whether you're on your way to school or leaving school, whether you're waking up to get ready for work or you're clocking out, or even if you're just chilling for the day and doing nothing at all. Every day is a new one and you decide how you want to start the day.",
      "comment_score": 7508,
      "playlist_id": "PLfr_88dG22s3J90Dm_bZkjC8D3kE-x_ta"
    },
    {
      "artist": "Matt Maltese",
      "song": "As the World Caves In",
      "spotify_id": "3NM41PVVUr0ceootKAtkAj",
      "spotify_uri": "spotify:track:3NM41PVVUr0ceootKAtkAj",
      "source_url": "https://youtube.com/watch?v=SqDjQPoJxiw",
      "source": "youtube",
      "post_title": "Whimsical Music Playlist",
      "comment_text": "“OH GIRLL ITS YOUU “ and “ AS THE ATOM BOMB LOCKS IN” gave me chills",
      "comment_score": 65392,
      "playlist_id": "PLfr_88dG22s3J90Dm_bZkjC8D3kE-x_ta"
    },
    {
      "artist": "proderics",
      "song": "strangers",
      "spotify_id": "2QdcmNlQdW8iA4JEg29cgx",
      "spotify_uri": "spotify:track:2QdcmNlQdW8iA4JEg29cgx",
      "source_url": "https://youtube.com/watch?v=QFPe7MKEmU8",
      "source": "youtube",
      "post_title": "Whimsy Twee playlist !! 🍎🍵🍏🍁🍀🎨🧶🎶💊🐠📺",
      "comment_text": "Life, at its core, is a vast, uncharted journey of self-discovery, yet we often find ourselves confined by invisible chains—expectations, traditions, and societal norms that dictate our paths before we even realize we have a choice. If we are not meant to explore, to carve our own destinies, then why were we given minds capable of questioning, dreaming, and defying? Are we merely vessels to fulfill the blueprints laid out by others, or do we owe it to ourselves to break free, to chase fulfillment on our own terms? The fear of stepping outside these predetermined lines keeps many bound, yet true existence lies in the courage to embrace uncertainty, to live not as we are told, but as we desire. If we surrender our freedom to the future designed by others, do we ever truly live at all?",
      "comment_score": 189,
      "playlist_id": "PLSXvKQWZp1RKFER6b2vvfQt-KSFYWojls"
    },
    {
      "artist": "Hot Mulligan",
      "song": "This Song is Called it’s Called What’s it Called",
      "spotify_id": "08KuqoLtwhpdqzPfmQCfpV",
      "spotify_uri": "spotify:track:08KuqoLtwhpdqzPfmQCfpV",
      "source_url": "https://youtube.com/watch?v=_RT674z7sd0",
      "source": "youtube",
      "post_title": "Whimsy Twee playlist !! 🍎🍵🍏🍁🍀🎨🧶🎶💊🐠📺",
      "comment_text": "Pink pantheress if she played guitar",
      "comment_score": 262,
      "playlist_id": "PLSXvKQWZp1RKFER6b2vvfQt-KSFYWojls"
    },
    {
      "artist": "beabadoobee",
      "song": "Apple Cider",
      "spotify_id": "5xA5MggKc3aQxuOzNzPUWB",
      "spotify_uri": "spotify:track:5xA5MggKc3aQxuOzNzPUWB",
      "source_url": "https://youtube.com/watch?v=laDnsiKURTQ",
      "source": "youtube",
      "post_title": "Whimsy Twee playlist !! 🍎🍵🍏🍁🍀🎨🧶🎶💊🐠📺",
      "comment_text": "I'll never get tired of her music. I hope one day she’ll get the recognition she deserves <3",
      "comment_score": 6605,
      "playlist_id": "PLSXvKQWZp1RKFER6b2vvfQt-KSFYWojls"
    },
    {
      "artist": "Tiny Waves",
      "song": "Undertale Medley (From \"Undertale\")",
      "spotify_id": "2YfFKIyuWamkuxtE8YvG6p",
      "spotify_uri": "spotify:track:2YfFKIyuWamkuxtE8YvG6p",
      "source_url": "https://youtube.com/watch?v=iPf5B7VwNjw",
      "source": "youtube",
      "post_title": "Whimsy Twee playlist !! 🍎🍵🍏🍁🍀🎨🧶🎶💊🐠📺",
      "comment_text": "I'm worried that the song is so good that it makes me feel bad. On the other hand, I sincerely thank whoever created this wonderful video.💗",
      "comment_score": 38,
      "playlist_id": "PLSXvKQWZp1RKFER6b2vvfQt-KSFYWojls"
    },
    {
      "artist": "Pyotr Ilyich Tchaikovsky",
      "song": "Swan Lake Suite, Op. 20a: I. Scene \"Swan Theme\". Moderato",
      "spotify_id": "1TQ2UYCN7nhfj3cfcFC76V",
      "spotify_uri": "spotify:track:1TQ2UYCN7nhfj3cfcFC76V",
      "source_url": "https://youtube.com/watch?v=9cNQFB0TDfY",
      "source": "youtube",
      "post_title": "Whimsy Twee playlist !! 🍎🍵🍏🍁🍀🎨🧶🎶💊🐠📺",
      "comment_text": "tchaikovskij dropped the hardest beat and thought we wouldn't notice 💀",
      "comment_score": 26034,
      "playlist_id": "PLSXvKQWZp1RKFER6b2vvfQt-KSFYWojls"
    },
    {
      "artist": "r u s s e l b u c k",
      "song": "Just Be Competent",
      "spotify_id": "2q5JF3bRPDeAS8EO8KIjEH",
      "spotify_uri": "spotify:track:2q5JF3bRPDeAS8EO8KIjEH",
      "source_url": "https://youtube.com/watch?v=_UqGrwCbxVI",
      "source": "youtube",
      "post_title": "Whimsy Twee playlist !! 🍎🍵🍏🍁🍀🎨🧶🎶💊🐠📺",
      "comment_text": "People always complain about songs ''getting too popular'' and not being able to gatekeep them anymore, but for creatures who live under a rock like me we genuinely thrive off of said popularity to find bangers.",
      "comment_score": 5327,
      "playlist_id": "PLSXvKQWZp1RKFER6b2vvfQt-KSFYWojls"
    },
    {
      "artist": "AURORA",
      "song": "Running with the Wolves",
      "spotify_id": "7uJqcrNhQ4hnJ2BoUNwuNg",
      "spotify_uri": "spotify:track:7uJqcrNhQ4hnJ2BoUNwuNg",
      "source_url": "https://youtube.com/watch?v=06ht9MyJLT4",
      "source": "youtube",
      "post_title": "Whimsical Music",
      "comment_text": "The scene this song is played during Wolfwalkers is honestly one of the most beautiful and emotional scenes in recent cinema!",
      "comment_score": 14989,
      "playlist_id": "PLtqtQ_ougDwf1sA2A1MP5TuhcqWxbkqjx"
    },
    {
      "artist": "Rose Betts",
      "song": "Irish Eyes",
      "spotify_id": "6BuNcxbUQyssRpHEBqmpLw",
      "spotify_uri": "spotify:track:6BuNcxbUQyssRpHEBqmpLw",
      "source_url": "https://youtube.com/watch?v=EhJD4ekxoxk",
      "source": "youtube",
      "post_title": "Whimsical Music",
      "comment_text": "I love the idea of me being \"a map of them all\" -- not only by heritage, but also because we are made of everyone we love and the marks we leave on them. If your sister says you have a restless soul, that's who you are to her. I have no Irish or English in my blood at all, and I'm also not told I have traveling feet etc., but it's amazing how this song is so much about Rose Betts, and at the same time it's about everyone.",
      "comment_score": 813,
      "playlist_id": "PLtqtQ_ougDwf1sA2A1MP5TuhcqWxbkqjx"
    },
    {
      "artist": "Taylor Swift",
      "song": "willow",
      "spotify_id": "0lx2cLdOt3piJbcaXIV74f",
      "spotify_uri": "spotify:track:0lx2cLdOt3piJbcaXIV74f",
      "source_url": "https://youtube.com/watch?v=RsEZmictANA",
      "source": "youtube",
      "post_title": "Whimsical Music",
      "comment_text": "\"not a lot going on at the moment\" times two!",
      "comment_score": 20647,
      "playlist_id": "PLtqtQ_ougDwf1sA2A1MP5TuhcqWxbkqjx"
    },
    {
      "artist": "Ekaterina Shelehova",
      "song": "Savage Daughter",
      "spotify_id": "0jZq0zDujagh2kLVYVGsN8",
      "spotify_uri": "spotify:track:0jZq0zDujagh2kLVYVGsN8",
      "source_url": "https://youtube.com/watch?v=tegev08KyHY",
      "source": "youtube",
      "post_title": "Whimsical Music",
      "comment_text": "I'm a pagan woman who has been disowned by my devout christian family for not fitting into their box. This song speaks to my soul.",
      "comment_score": 10333,
      "playlist_id": "PLtqtQ_ougDwf1sA2A1MP5TuhcqWxbkqjx"
    },
    {
      "artist": "Babyface Ray",
      "song": "Ron Artest",
      "spotify_id": "4Wlz0HsHZlJy0NDK2h6jq6",
      "spotify_uri": "spotify:track:4Wlz0HsHZlJy0NDK2h6jq6",
      "source_url": "https://youtube.com/watch?v=__CRWE-L45k",
      "source": "youtube",
      "post_title": "Goofy ahh music playlist",
      "comment_text": "can't believe it's taken 8 years for you all to realise the true lyrics:\n\nTURI IP IP IP",
      "comment_score": 53659,
      "playlist_id": "PLB9XhdHR9kamu2UuipyzZvZOhD7XHx5Vg"
    },
    {
      "artist": "Tmsoft’s White Noise Sleep Sounds",
      "song": "Relaxed Scene - with Rain - Extended",
      "spotify_id": "6GBCeoZ1vQjMWTFJPTH7zZ",
      "spotify_uri": "spotify:track:6GBCeoZ1vQjMWTFJPTH7zZ",
      "source_url": "https://youtube.com/watch?v=0W80OqcWnqc",
      "source": "youtube",
      "post_title": "Goofy ahh music playlist",
      "comment_text": "We played, we tried\n We laughed, we cried \nWe succeeded, we died \nWe respawned and thrived\nWe hid, we searched\nWe played and obeyed\nFrom Adopt Me to Doors\nFrom Murder Mystery to Brookhaven\nEach and every game we cherish\nEach and every holds the joy\nThe laughs and cheers\nThe cries and fears\nI thank Roblox for making my childhood better\nMuch better than ‘good’ I speak for everyone here\nWhen I say it's not the game of the year\nIt’s the game of the century \nAs it offered us plenty and more to come\nSo close your eyes just once more\nAnd hear the footsteps and the voice\nDeep inside you still lives Roblox\nAnd the sweet sounds of your childhood start to chime\nYou feel yourself back in time\nOne last thing, for me to say\nJust have a very good day\nAlso for you to never forget this game\nNor the journey that came\nBecause it will always be inside \nDeep down\nWhich I hope you all read\nAs I would love it if this poem and the game were remembered once I’m dead\n\nRemixed from the Minecraft version. Just thought Roblox needed one too! :)",
      "comment_score": 7188,
      "playlist_id": "PLB9XhdHR9kamu2UuipyzZvZOhD7XHx5Vg"
    },
    {
      "artist": "Decuma",
      "song": "basketball.",
      "spotify_id": "0n3WsS4Oo6zLKxCuQErK06",
      "spotify_uri": "spotify:track:0n3WsS4Oo6zLKxCuQErK06",
      "source_url": "https://youtube.com/watch?v=SJqEyOuZS2A",
      "source": "youtube",
      "post_title": "Goofy ahh music playlist",
      "comment_text": "I swear Gabby and Eddie are so cute together, especially when she brings him things without him even asking.",
      "comment_score": 3612,
      "playlist_id": "PLB9XhdHR9kamu2UuipyzZvZOhD7XHx5Vg"
    },
    {
      "artist": "Wax",
      "song": "No Smoking In The House",
      "spotify_id": "1GX1y3y78i7S4yIG7UNySU",
      "spotify_uri": "spotify:track:1GX1y3y78i7S4yIG7UNySU",
      "source_url": "https://youtube.com/watch?v=vbG5eFZVY78",
      "source": "youtube",
      "post_title": "GOOFY AHH SONGS",
      "comment_text": "This made me say “bruh”",
      "comment_score": 24,
      "playlist_id": "PLMr5zsNgKvmXKnJ2hDcaQakhHhAtcz2RR"
    },
    {
      "artist": "ZAPPA",
      "song": "IMPREZA WWA",
      "spotify_id": "64HNye1BDPu3kUzPstKDWr",
      "spotify_uri": "spotify:track:64HNye1BDPu3kUzPstKDWr",
      "source_url": "https://youtube.com/watch?v=aAPKU9TyEBw",
      "source": "youtube",
      "post_title": "GOOFY AHH SONGS",
      "comment_text": "I couldn’t even edge to this, I exploded immediately!!! Clean up on aisle MY PANTS😂😂😂",
      "comment_score": 36,
      "playlist_id": "PLMr5zsNgKvmXKnJ2hDcaQakhHhAtcz2RR"
    },
    {
      "artist": "Adam Turley",
      "song": "elevator music",
      "spotify_id": "4qO7XJmbjpyrz1T028uz3j",
      "spotify_uri": "spotify:track:4qO7XJmbjpyrz1T028uz3j",
      "source_url": "https://youtube.com/watch?v=xy_NKN75Jhw",
      "source": "youtube",
      "post_title": "GOOFY AHH SONGS",
      "comment_text": "*_We'll be right back after this short intermission_*",
      "comment_score": 17403,
      "playlist_id": "PLMr5zsNgKvmXKnJ2hDcaQakhHhAtcz2RR"
    },
    {
      "artist": "Pulses.",
      "song": "Exist Warp Brakes",
      "spotify_id": "5QKqoRxU1NUlIG39ERPlWR",
      "spotify_uri": "spotify:track:5QKqoRxU1NUlIG39ERPlWR",
      "source_url": "https://youtube.com/watch?v=ONzntmMFXGE",
      "source": "youtube",
      "post_title": "GOOFY AHH SONGS",
      "comment_text": "The song 🗿  \r\nThe beat 🗿  \r\nThe creator 🗿  \r\nThe producer 🗿  \r\nThe instrumental 🗿  \r\nThe software used to create this beat 🗿  \r\nThe synthesizers 🗿  \r\nThe drums 🗿  \r\nThe bassline 🗿  \r\nThe guitar riff 🗿  \r\nThe background melodies 🗿  \r\nThe sound effects 🗿  \r\nThe sound engineers 🗿  \r\nThe autotune 🗿  \r\nThe studio where it was recorded 🗿  \r\nThe recording booth 🗿  \r\nThe microphone 🗿  \r\nThe mixing board 🗿  \r\nThe mastering process 🗿  \r\nThe final touches 🗿  \r\nThe speakers blasting the sound 🗿  \r\nThe headphones 🗿  \r\nThe earbuds 🗿  \r\nThe phone playing the track 🗿  \r\nThe Bluetooth connection 🗿  \r\nThe AUX cord 🗿  \r\nThe radio stations broadcasting it 🗿  \r\nThe vibrations in the air 🗿  \r\nThe sound waves 🗿  \r\nThe subwoofer thumping 🗿  \r\nThe car stereo booming 🗿  \r\nThe vibrations in the walls 🗿  \r\nThe windows rattling 🗿  \r\nThe ones listening to it 🗿  \r\nThe neurons firing in your brain as you vibe to it 🗿  \r\nThe dopamine surge 🗿  \r\nThe adrenaline rush 🗿  \r\nThe goosebumps 🗿  \r\nThe fans cheering 🗿  \r\nThe viewers on YouTube 🗿  \r\nThe thumbs up on the video 🗿  \r\nThe comments left by fans 🗿  \r\nThe pinned comment 🗿  \r\nThe one who commented first 🗿  \r\nThe guy who got ratio'd 🗿  \r\nThe first person who heard it 🗿  \r\nThe person who replayed it 50 times 🗿  \r\nThe guy who added it to his playlist 🗿  \r\nThe person who saved it offline 🗿  \r\nThe one who recommended it to his friends 🗿  \r\nThe one who shared it in a group chat 🗿  \r\nThe people bobbing their heads 🗿  \r\nThe guy lip-syncing 🗿  \r\nThe DJs spinning this track 🗿  \r\nThe party where this was the vibe 🗿  \r\nThe house party shaking with the beat 🗿  \r\nThe concert where it was played 🗿  \r\nThe rave where the lights matched the music 🗿  \r\nThe crowd jumping to the beat 🗿  \r\nThe stage lights 🗿  \r\nThe speakers on stage 🗿  \r\nThe pyrotechnics 🗿  \r\nThe laser lights 🗿  \r\nThe fog machine 🗿  \r\nThe fireworks in the background 🗿  \r\nThe mosh pit forming 🗿  \r\nThe people getting hyped 🗿  \r\nThe hands up in the air 🗿  \r\nThe festival where this track was played 🗿  \r\nThe afterparty 🗿  \r\nThe Uber ride home blasting it 🗿  \r\nThe person humming the melody 🗿  \r\nThe muscle contractions making you dance 🗿  \r\nThe people posting fire emojis 🗿  \r\nThe GIF reactions 🗿  \r\nThe comments section 🗿  \r\nThe algorithms pushing this to the top 🗿  \r\nThe YouTube trending page 🗿  \r\nThe Spotify viral charts 🗿  \r\nThe people sharing it on social media 🗿  \r\nThe Instagram stories 🗿  \r\nThe TikTok videos 🗿  \r\nThe reels 🗿  \r\nThe algorithms pushing it further 🗿  \r\nThe fan-made remixes 🗿  \r\nThe nightcore version 🗿  \r\nThe slowed + reverb version 🗿  \r\nThe 1-hour loop 🗿  \r\nThe fans listening on repeat 🗿  \r\nThe house shaking from the bass 🗿  \r\nThe car subwoofer booming 🗿  \r\nThe windows vibrating 🗿  \r\nThe neighbors complaining 🗿  \r\nThe people putting it on during a party 🗿  \r\nThe road trips with this on repeat 🗿  \r\nThe Spotify Wrapped featuring this track 🗿  \r\nThe year-end list 🗿  \r\nThe workout playlist 🗿  \r\nThe gym bros blasting it during sets 🗿  \r\nThe headphones on full blast 🗿  \r\nThe Bluetooth speakers in the park 🗿  \r\nThe person running to the beat 🗿  \r\nThe joggers 🗿  \r\nThe cyclists 🗿  \r\nThe gym 🗿  \r\nThe squat rack 🗿  \r\nThe leg press 🗿  \r\nThe dumbbells 🗿  \r\nThe barbells 🗿  \r\nThe kettlebells 🗿  \r\nThe bench press 🗿  \r\nThe incline bench 🗿  \r\nThe rowing machine 🗿  \r\nThe spin bike 🗿  \r\nThe treadmills 🗿  \r\nThe elliptical 🗿  \r\nThe weights clanking 🗿  \r\nThe gym bros grunting 🗿  \r\nThe cardio section 🗿  \r\nThe squat racks 🗿  \r\nThe weight plates 🗿  \r\nThe chalk for gripping 🗿  \r\nThe protein shakes 🗿  \r\nThe supplements 🗿  \r\nThe jars of creatine 🗿  \r\nThe jars of BCAAs 🗿  \r\nThe pre-workout 🗿  \r\nThe protein powder 🗿  \r\nThe protein bars 🗿  \r\nThe energy drinks 🗿  \r\nThe guy hitting a PR 🗿  \r\nThe high-fives after hitting a new personal record 🗿  \r\nThe gym shoes 🗿  \r\nThe wrist wraps 🗿  \r\nThe lifting belts 🗿  \r\nThe gym clothes 🗿  \r\nThe sweatbands 🗿  \r\nThe shaker bottles 🗿  \r\nThe gym bags 🗿  \r\nThe powerlifting chalk 🗿  \r\nThe Bluetooth headphones 🗿  \r\nThe earbuds falling out mid-set 🗿  \r\nThe veins popping 🗿  \r\nThe sweat dripping 🗿  \r\nThe sweat-soaked shirt 🗿  \r\nThe adrenaline kicking in 🗿  \r\nThe guy doing extra reps 🗿  \r\nThe steam room after a workout 🗿  \r\nThe sauna 🗿  \r\nThe cold showers 🗿  \r\nThe post-workout soreness 🗿  \r\nThe foam roller 🗿  \r\nThe massage guns 🗿  \r\nThe stretching mats 🗿  \r\nThe mirrors reflecting those gains 🗿  \r\nThe bodyweight exercises 🗿  \r\nThe jump rope 🗿  \r\nThe planks 🗿  \r\nThe pull-up bar 🗿  \r\nThe gym lockers 🗿  \r\nThe water fountains 🗿  \r\nThe vending machines 🗿  \r\nThe pre-made meals 🗿  \r\nThe high-protein snacks 🗿  \r\nThe electrolytes 🗿  \r\nThe calorie counters 🗿  \r\nThe workout apps 🗿  \r\nThe fitness challenges 🗿  \r\nThe gym membership 🗿  \r\nThe recovery drinks 🗿  \r\nThe post-workout smoothies 🗿  \r\nThe sports massages 🗿  \r\nThe muscle fibers repairing 🗿  \r\nThe anabolic window 🗿  \r\nThe soreness after leg day 🗿  \r\nThe PRs being broken 🗿  \r\nThe progress photos 🗿  \r\nThe gym selfies 🗿  \r\nThe Instagram posts of gains 🗿  \r\nThe comments on those posts 🗿  \r\nThe likes on those posts 🗿  \r\nThe shares 🗿  \r\nThe stories reposting gym goals 🗿  \r\nThe fitness influencers 🗿  \r\nThe workout tutorials 🗿  \r\nThe lifting PRs 🗿  \r\nThe macros 🗿  \r\nThe meal prep 🗿  \r\nThe calories burned 🗿  \r\nThe fitness challenges 🗿  \r\nThe daily workout streak 🗿  \r\nThe biceps flexing 🗿  \r\nThe veins bulging 🗿  \r\nThe protein-rich meals 🗿  \r\nThe supplements 🗿  \r\nThe people saying \"one more set\" 🗿  \r\nThe squat depth 🗿  \r\nThe motivational quotes 🗿  \r\nThe workout music blasting in the background 🗿  \r\nThe gym attire 🗿  \r\nThe leggings 🗿  \r\nThe sweat-wicking shirts 🗿  \r\nThe tank tops 🗿  \r\nThe sports bras 🗿  \r\nThe lifting gloves 🗿  \r\nThe resistance bands 🗿  \r\nThe yoga mats 🗿 \r\nThe end of the universe 🗿  \r\nThe beginning of the next 🗿  \r\nThe dark matter around it 🗿  \r\nThe supermassive black hole 🗿  \r\nThe expansion of space 🗿  \r\nThe time dilation felt while vibing 🗿  \r\nThe energy permeating everything 🗿  \r\nThe strings of reality vibrating 🗿  \r\nThe particles dancing to the frequency 🗿  \r\nThe quantum fields affected 🗿  \r\nThe Big Bang itself 🗿  \r\nThe gravity of the situation 🗿  \r\nThe speed of light being surpassed 🗿  \r\nThe wormholes opening 🗿  \r\nThe alternate realities formed 🗿  \r\nThe cosmic dance of galaxies 🗿  \r\nThe infinite potential of existence 🗿  \r\nThe birth of stars as this plays 🗿  \r\nThe cosmic dust swirling 🗿  \r\nThe nebulae glowing 🗿  \r\nThe fusion reactions ignited by this song 🗿  \r\nThe pulsars pulsing to the rhythm 🗿  \r\nThe supernovas exploding in sync 🗿  \r\nThe black holes warping space-time 🗿  \r\nThe quasar beams slicing through galaxies 🗿  \r\nThe cosmic radiation vibrating 🗿  \r\nThe entire universe humming with the beat 🗿  \r\nThe parallel realities merging 🗿  \r\nThe time loops repeating this song 🗿  \r\nThe multiverse syncing to this frequency 🗿  \r\nThe fourth dimension bending around it 🗿  \r\nThe fifth-dimensional beings nodding their heads 🗿  \r\nThe strings of the universe vibrating with every note 🗿  \r\nThe quantum entanglement happening between listeners 🗿  \r\nThe gravitational waves caused by the bass 🗿  \r\nThe energy of every atom responding 🗿  \r\nThe dark energy accelerating its expansion 🗿  \r\nThe curvature of space bending around the sound 🗿  \r\nThe cosmic background radiation absorbing the melody 🗿  \r\nThe dimensions beyond our understanding feeling this 🗿   \r\nThe philosophers contemplating its meaning 🗿  \r\nThe poets writing verses inspired by it 🗿  \r\nThe artists painting to the sound of the beat 🗿  \r\nThe dancers moving in perfect sync 🗿  \r\nThe actors making cinematic masterpieces with this in the background 🗿  \r\nThe screenwriters crafting epic scenes set to this song 🗿  \r\nThe novelists writing entire sagas inspired by its rhythm 🗿  \r\nThe architects designing buildings that pulse with its beat 🗿  \r\nThe cities shaped by the energy of this track 🗿  \r\nThe lights of the world flickering to its tempo 🗿  \r\nThe oceans rising and falling with the flow 🗿  \r\nThe tides pulled by the gravitational pull of this song 🗿  \r\nThe winds across the world swirling in sync 🗿    \r\nThe essence of life itself flowing through the melody 🗿  \r\nThe fabric of reality stretching as the song pulses 🗿  \r\nThe energy in every atom accelerating 🗿  \r\nThe vibrations of the universe reaching their peak 🗿  \r\nThe infinite possibilities unfolding with every beat 🗿  \r\nThe ultimate truth of existence being revealed 🗿  \r\nThe very meaning of life unraveling in the song 🗿  \r\nThe purpose of everything aligning with the rhythm 🗿  \r\nThe cosmos awakening to its true nature 🗿  \r\nThe divine spark within all beings igniting 🗿  \r\nThe universe itself ascending 🗿  \r\nThe final realization that we are all one with the beat 🗿  \r\nme 🗿  \r\nyou 🗿  \r\nur girlfriend 🗿  \r\nur dog 🗿  \r\nohio sigmas 🗿  \r\nmr beast followers 🗿  \r\ngymrats 🗿  \r\naverage phonk user 🗿  \r\nthe FINAL BOSS 🗿  \r\nur skills 🗿  \r\nthe people 🗿  \r\nmy N word homie 🗿  \r\nur food 🗿  \r\nPeople who liked this comment 🗿",
      "comment_score": 905,
      "playlist_id": "PLMr5zsNgKvmXKnJ2hDcaQakhHhAtcz2RR"
    },
    {
      "artist": "Kevin MacLeod",
      "song": "Monkeys Spinning Monkeys",
      "spotify_id": "4aWIEDu1UdHuFLHHL10JVk",
      "spotify_uri": "spotify:track:4aWIEDu1UdHuFLHHL10JVk",
      "source_url": "https://youtube.com/watch?v=pr42azVZi3o",
      "source": "youtube",
      "post_title": "GOOFY AHH SONGS",
      "comment_text": "lets have a moment for the people that couldn't find this sound...",
      "comment_score": 14653,
      "playlist_id": "PLMr5zsNgKvmXKnJ2hDcaQakhHhAtcz2RR"
    },
    {
      "artist": "Dollarz$",
      "song": "Runway",
      "spotify_id": "2AfRUgokgvSTs5KRscZYsK",
      "spotify_uri": "spotify:track:2AfRUgokgvSTs5KRscZYsK",
      "source_url": "https://youtube.com/watch?v=TtXFsJjCrzM",
      "source": "youtube",
      "post_title": "GOOFY AHH MUSIC SKIBIDI OHIO",
      "comment_text": "Не надо сливать треки ребята. Дождитесь дропа. Всех обнял",
      "comment_score": 208,
      "playlist_id": "PLQ-JlC-6sTj8fkebprakG77xrZLn926Sz"
    },
    {
      "artist": "FUCKYOURCLIQUE",
      "song": "VAI A GIOCARE CON I FIGLI DEI VICINI, I FIGLI DEI VICINI:",
      "spotify_id": "5ckSsmBD5LARM0VtuuJmbY",
      "spotify_uri": "spotify:track:5ckSsmBD5LARM0VtuuJmbY",
      "source_url": "https://youtube.com/watch?v=TirKBifH3Wg",
      "source": "youtube",
      "post_title": "GOOFY AHH MUSIC SKIBIDI OHIO",
      "comment_text": "We need a full version of this piece of art bro",
      "comment_score": 10423,
      "playlist_id": "PLQ-JlC-6sTj8fkebprakG77xrZLn926Sz"
    },
    {
      "artist": "J.Geco",
      "song": "The Chicken Song (10 Years Anniversary)",
      "spotify_id": "2AwvyGylYyf2qopZNnUlA1",
      "spotify_uri": "spotify:track:2AwvyGylYyf2qopZNnUlA1",
      "source_url": "https://youtube.com/watch?v=msSc7Mv0QHY",
      "source": "youtube",
      "post_title": "Stupid annoying songs that&#39;s actually funny",
      "comment_text": "Why are you all listening to this! i don't even get money go awayyyy",
      "comment_score": 56756,
      "playlist_id": "PLU_hIjXAHm2FGqesqVXg_fOkTy7y-VfwC"
    },
    {
      "artist": "PIKOTARO",
      "song": "PPAP (Pen Pineapple Apple Pen) - Long Version",
      "spotify_id": "4bw49rU057FSUTpGF4pnxq",
      "spotify_uri": "spotify:track:4bw49rU057FSUTpGF4pnxq",
      "source_url": "https://youtube.com/watch?v=Ct6BUPvE2sM",
      "source": "youtube",
      "post_title": "Stupid annoying songs that&#39;s actually funny",
      "comment_text": "if after 6 years you randomly search this up you have my respect",
      "comment_score": 46112,
      "playlist_id": "PLU_hIjXAHm2FGqesqVXg_fOkTy7y-VfwC"
    }
  ]
}